.coveragerc
.gitignore
.travis.yml
AUTHORS.rst
CHANGELOG.rst
LICENSE.txt
README.rst
justfile
requirements.txt
setup.cfg
setup.py
docs/Makefile
docs/authors.rst
docs/changelog.rst
docs/conf.py
docs/index.rst
docs/license.rst
docs/_static/.gitignore
examples/readme_example.py
src/conebeam_projector/BackProjectionKernel.cu
src/conebeam_projector/ForwardProjectionKernel.cu
src/conebeam_projector/__init__.py
src/conebeam_projector/_projection.py
src/conebeam_projector/_utils.py
src/conebeam_projector.egg-info/PKG-INFO
src/conebeam_projector.egg-info/SOURCES.txt
src/conebeam_projector.egg-info/dependency_links.txt
src/conebeam_projector.egg-info/not-zip-safe
src/conebeam_projector.egg-info/requires.txt
src/conebeam_projector.egg-info/top_level.txt
tests/test_projector.py
tests/travis_install.sh