Metadata-Version: 2.1
Name: conebeam-projector
Version: 0.1.2
Summary: Cone Beam Projector in Python
Home-page: https://github.com/theHamsta/conebeam_projector
Author: Stephan Seitz
Author-email: stephan.seitz@fau.de
License: GPLv3
Project-URL: Documentation, https://pyscaffold.org/
Platform: any
Classifier: Development Status :: 4 - Beta
Classifier: Programming Language :: Python
Provides-Extra: testing
